{"TEK\u0130RDA\u011e": {"elevation": "4", "measurement": {"05 May\u0131s - 02.49": {"weather": "\u00c7ok Bulutlu", "temperature": "13,2", "rainfall": "NoInfo", "wind": "transform: rotate(313deg);", "windspeed": "6", "humidty": "86", "pressureAct": "1017,2", "pressureRed": "1017,6"}, "05 May\u0131s - 03.04": {"weather": "\u00c7ok Bulutlu", "temperature": "13,3", "rainfall": "0,0", "wind": "transform: rotate(1deg);", "windspeed": "8", "humidty": "86", "pressureAct": "1017,2", "pressureRed": "1017,6"}}}, "HAYRABOLU": {"elevation": "108", "measurement": {"05 May\u0131s - 02.49": {"weather": "\u00c7ok Bulutlu", "temperature": "11,5", "rainfall": "NoInfo", "wind": "transform: rotate(349deg);", "windspeed": "5", "humidty": "95", "pressureAct": "1003,5", "pressureRed": "1016,2"}, "05 May\u0131s - 03.04": {"weather": "\u00c7ok Bulutlu", "temperature": "11,5", "rainfall": "0,0", "wind": "transform: rotate(333deg);", "windspeed": "8", "humidty": "95", "pressureAct": "1003,4", "pressureRed": "1016,1"}}}, "MALKARA": {"elevation": "207", "measurement": {"05 May\u0131s - 02.49": {"weather": "\u00c7ok Bulutlu", "temperature": "11,4", "rainfall": "NoInfo", "wind": "transform: rotate(38deg);", "windspeed": "8", "humidty": "92", "pressureAct": "993,4", "pressureRed": "1017,8"}, "05 May\u0131s - 02.58": {"weather": "\u00c7ok Bulutlu", "temperature": "11,4", "rainfall": "NoInfo", "wind": "transform: rotate(22deg);", "windspeed": "13", "humidty": "92", "pressureAct": "993,3", "pressureRed": "1017,7"}}}, "MALKARA/DO\u011eANK\u00d6Y": {"elevation": "248", "measurement": {"05 May\u0131s - 02.49": {"weather": "\u00c7ok Bulutlu", "temperature": "11,4", "rainfall": "NoInfo", "wind": "NoInfo", "windspeed": "NoInfo", "humidty": "100", "pressureAct": "NoInfo", "pressureRed": "NoInfo"}, "05 May\u0131s - 03.04": {"weather": "\u00c7ok Bulutlu", "temperature": "11,2", "rainfall": "0,0", "wind": "NoInfo", "windspeed": "NoInfo", "humidty": "100", "pressureAct": "NoInfo", "pressureRed": "NoInfo"}}}, "MARMARAERE\u011eL\u0130S\u0130": {"elevation": "49", "measurement": {"05 May\u0131s - 02.48": {"weather": "\u00c7ok Bulutlu", "temperature": "11,4", "rainfall": "NoInfo", "wind": "transform: rotate(25deg);", "windspeed": "8", "humidty": "84", "pressureAct": "NoInfo", "pressureRed": "NoInfo"}, "05 May\u0131s - 03.03": {"weather": "\u00c7ok Bulutlu", "temperature": "11,4", "rainfall": "0,0", "wind": "transform: rotate(22deg);", "windspeed": "13", "humidty": "84", "pressureAct": "NoInfo", "pressureRed": "NoInfo"}}}, "MURATLI": {"elevation": "113", "measurement": {"05 May\u0131s - 02.49": {"weather": "\u00c7ok Bulutlu", "temperature": "10,5", "rainfall": "NoInfo", "wind": "transform: rotate(22deg);", "windspeed": "10", "humidty": "92", "pressureAct": "NoInfo", "pressureRed": "NoInfo"}, "05 May\u0131s - 03.04": {"weather": "\u00c7ok Bulutlu", "temperature": "10,7", "rainfall": "0,0", "wind": "transform: rotate(27deg);", "windspeed": "11", "humidty": "93", "pressureAct": "NoInfo", "pressureRed": "NoInfo"}}}, "S\u00dcLEYMANPA\u015eA/BANARLI MAHALLES\u0130": {"elevation": "139", "measurement": {"05 May\u0131s - 02.49": {"weather": "\u00c7ok Bulutlu", "temperature": "11,6", "rainfall": "NoInfo", "wind": "NoInfo", "windspeed": "NoInfo", "humidty": "90", "pressureAct": "NoInfo", "pressureRed": "NoInfo"}, "05 May\u0131s - 03.04": {"weather": "\u00c7ok Bulutlu", "temperature": "11,2", "rainfall": "0,0", "wind": "NoInfo", "windspeed": "NoInfo", "humidty": "90", "pressureAct": "NoInfo", "pressureRed": "NoInfo"}}}, "TEK\u0130RDA\u011e \u00c7ORLU HAVAL\u0130MANI": {"elevation": "160", "measurement": {"05 May\u0131s - 02.50": {"weather": "\u00c7ok Bulutlu", "temperature": "11,1", "rainfall": "NoInfo", "wind": "transform: rotate(20deg);", "windspeed": "22", "humidty": "90", "pressureAct": "998,5", "pressureRed": "1017,6"}}}, "TEK\u0130RDA\u011e/SARAY": {"elevation": "160", "measurement": {"05 May\u0131s - 02.49": {"weather": "\u00c7ok Bulutlu", "temperature": "10,9", "rainfall": "NoInfo", "wind": "transform: rotate(68deg);", "windspeed": "18", "humidty": "98", "pressureAct": "NoInfo", "pressureRed": "NoInfo"}, "05 May\u0131s - 03.04": {"weather": "\u00c7ok Bulutlu", "temperature": "10,8", "rainfall": "0,0", "wind": "transform: rotate(61deg);", "windspeed": "15", "humidty": "98", "pressureAct": "NoInfo", "pressureRed": "NoInfo"}}}, "\u015eARK\u00d6Y": {"elevation": "10", "measurement": {"05 May\u0131s - 02.49": {"weather": "\u00c7ok Bulutlu", "temperature": "14,3", "rainfall": "NoInfo", "wind": "transform: rotate(72deg);", "windspeed": "5", "humidty": "92", "pressureAct": "1016,8", "pressureRed": "1017,9"}, "05 May\u0131s - 03.04": {"weather": "\u00c7ok Bulutlu", "temperature": "14,3", "rainfall": "0,0", "wind": "transform: rotate(85deg);", "windspeed": "4", "humidty": "92", "pressureAct": "1016,8", "pressureRed": "1017,9"}}}, "KAPAKLI": {"elevation": "246", "measurement": {"05 May\u0131s - 02.49": {"weather": "Az Bulutlu", "temperature": "10,2", "rainfall": "NoInfo", "wind": "transform: rotate(18deg);", "windspeed": "18", "humidty": "91", "pressureAct": "NoInfo", "pressureRed": "NoInfo"}, "05 May\u0131s - 03.04": {"weather": "Az Bulutlu", "temperature": "10,3", "rainfall": "0,0", "wind": "transform: rotate(12deg);", "windspeed": "15", "humidty": "91", "pressureAct": "NoInfo", "pressureRed": "NoInfo"}}}, "ERGENE/VAKIFLAR BELDES\u0130": {"elevation": "167", "measurement": {"05 May\u0131s - 02.49": {"weather": "A\u00e7\u0131k", "temperature": "10,6", "rainfall": "NoInfo", "wind": "NoInfo", "windspeed": "NoInfo", "humidty": "88", "pressureAct": "NoInfo", "pressureRed": "NoInfo"}, "05 May\u0131s - 03.04": {"weather": "A\u00e7\u0131k", "temperature": "10,5", "rainfall": "0,0", "wind": "NoInfo", "windspeed": "NoInfo", "humidty": "88", "pressureAct": "NoInfo", "pressureRed": "NoInfo"}}}, "MARMARA ERE\u011eL\u0130S\u0130 BAL.BAR.ANA MEND\u0130REK FENER\u0130": {"elevation": "10", "measurement": {"05 May\u0131s - 02.45": {"weather": "A\u00e7\u0131k", "temperature": "11,5", "rainfall": "NoInfo", "wind": "transform: rotate(49deg);", "windspeed": "13", "humidty": "95", "pressureAct": "1014,8", "pressureRed": "1016"}, "05 May\u0131s - 02.59": {"weather": "A\u00e7\u0131k", "temperature": "11,6", "rainfall": "NoInfo", "wind": "transform: rotate(28deg);", "windspeed": "9", "humidty": "94", "pressureAct": "1014,9", "pressureRed": "1016,1"}}}, "\u00c7ERKEZK\u00d6Y": {"elevation": "160", "measurement": {"05 May\u0131s - 02.49": {"weather": "A\u00e7\u0131k", "temperature": "11,4", "rainfall": "NoInfo", "wind": "transform: rotate(51deg);", "windspeed": "11", "humidty": "91", "pressureAct": "1000,8", "pressureRed": "1019,8"}, "05 May\u0131s - 03.04": {"weather": "A\u00e7\u0131k", "temperature": "11,2", "rainfall": "0,0", "wind": "transform: rotate(48deg);", "windspeed": "12", "humidty": "91", "pressureAct": "1000,8", "pressureRed": "1019,8"}}}, "\u00c7ORLU": {"elevation": "145", "measurement": {"05 May\u0131s - 02.49": {"weather": "A\u00e7\u0131k", "temperature": "11,5", "rainfall": "NoInfo", "wind": "transform: rotate(39deg);", "windspeed": "2", "humidty": "94", "pressureAct": "999,5", "pressureRed": "1016,6"}, "05 May\u0131s - 03.04": {"weather": "A\u00e7\u0131k", "temperature": "11,1", "rainfall": "0,0", "wind": "transform: rotate(23deg);", "windspeed": "7", "humidty": "95", "pressureAct": "999,6", "pressureRed": "1016,8"}}}, "\u015eARK\u00d6Y/GANOS DA\u011eI": {"elevation": "743", "measurement": {"05 May\u0131s - 01.25": {"weather": "NoInfo", "temperature": "12,4", "rainfall": "NoInfo", "wind": "NoInfo", "windspeed": "NoInfo", "humidty": "100", "pressureAct": "NoInfo", "pressureRed": "NoInfo"}}}}